millibot/__init__.py
millibot/millibot.py
millibot/tests/__init__.py
millibot/tests/test_millibot.py
millibot-0.1.dist-info/DESCRIPTION.rst
millibot-0.1.dist-info/METADATA
millibot-0.1.dist-info/RECORD
millibot-0.1.dist-info/WHEEL
millibot-0.1.dist-info/metadata.json
millibot-0.1.dist-info/top_level.txt
