Metadata-Version: 2.0
Name: millibot
Version: 0.1
Summary: A minimalist BOT framework.
Home-page: https://github.com/rajasimon/millibot
Author: Raja Simon
Author-email: rajasimon@icloud.com
License: MIT
Platform: UNKNOWN
